root_pack/__init__.py
root_pack/ch.csv
root_pack/change.csv
root_pack/dictionary.txt
root_pack/example.csv
root_pack/suffixdvithva.txt
root_pack/suffixmorph.txt
root_pack/verb.txt
root_pack-1.1.1.dist-info/LICENSE.txt
root_pack-1.1.1.dist-info/METADATA
root_pack-1.1.1.dist-info/WHEEL
root_pack-1.1.1.dist-info/top_level.txt
root_pack-1.1.1.dist-info/RECORD
