Metadata-Version: 2.1
Name: root-pack
Version: 1.1.1
Summary: Extract root from a Malayalam word
Home-page: https://gitlab.com/icfoss/Malayalam-Computing/Root_Extractor_for_Malayalam
Author: Jincy Baby
Author-email: jincybaby@icfoss.org
License: GNU Public License
Platform: UNKNOWN
Classifier: Programming Language :: Python :: 3
Classifier: Operating System :: OS Independent
